pyytdata/__init__.py
pyytdata/pyytdata.py
pyytdata/util/__init__.py
pyytdata/util/fetcher.py
pyytdata/util/info.py
pyytdata/util/ytdata.py
pyytdata-0.3.0.dist-info/LICENSE
pyytdata-0.3.0.dist-info/METADATA
pyytdata-0.3.0.dist-info/WHEEL
pyytdata-0.3.0.dist-info/top_level.txt
pyytdata-0.3.0.dist-info/RECORD
