Metadata-Version: 2.1
Name: pyytdata
Version: 0.3.0
Summary: A python library which provides all possible metadata of YouTube videos.
Home-page: https://github.com/princekrroshan01/youtube-api-wrapper
Author: Prince Roshan
Author-email: princekrroshan01@gmail.com
License: MIT
Keywords: youtube-apirecommend-youtube-videos,youtube-data,python,wrapper,youtube-data-api-v3,youtube-api-wrapper,youtube-api-v3
Classifier: Programming Language :: Python :: 3.7
Classifier: Programming Language :: Python :: 3.8
Classifier: Programming Language :: Python :: 3.9
Classifier: Programming Language :: Python :: 3.10
Classifier: Programming Language :: Python :: 3.11
Classifier: Operating System :: OS Independent
Requires-Python: >=3.7
License-File: LICENSE
Requires-Dist: google-api-python-client
